dice_checker/__init__.py
dice_checker/py.typed
dice_checker/roll.py
dice_checker-0.0.4.dist-info/METADATA
dice_checker-0.0.4.dist-info/WHEEL
dice_checker-0.0.4.dist-info/licenses/LICENSE
dice_checker-0.0.4.dist-info/RECORD
