Metadata-Version: 2.4
Name: dice-checker
Version: 0.0.4
Summary: Simple dice manipulation library allowing to compute probabilities of complex dice rolls
Project-URL: Repository, https://github.com/rguillon/dicer
Author-email: Renaud Guillon <renaud.guillon@gmail.com>
License-Expression: MIT
License-File: LICENSE
Classifier: Development Status :: 5 - Production/Stable
Classifier: Intended Audience :: Developers
Classifier: Operating System :: OS Independent
Classifier: Programming Language :: Python
Classifier: Programming Language :: Python :: 3
Classifier: Programming Language :: Python :: 3.11
Classifier: Programming Language :: Python :: 3.12
Classifier: Programming Language :: Python :: 3.13
Classifier: Typing :: Typed
Requires-Python: <4.0,>=3.10
Requires-Dist: matplotlib>=3.10.6
